uface_test_server_client/__init__.py
uface_test_server_client/cmd.py
uface_test_server_client/inference.py
uface_test_server_client/inference_stub.py
uface_test_server_client-0.0.8.dist-info/METADATA
uface_test_server_client-0.0.8.dist-info/WHEEL
uface_test_server_client-0.0.8.dist-info/top_level.txt
uface_test_server_client-0.0.8.dist-info/RECORD
