Metadata-Version: 2.1
Name: uface-test-server-client
Version: 0.0.8
Summary: UNKNOWN
Home-page: UNKNOWN
Author: HaoLiuHust
Author-email: haoliuhust@hotmail.com
License: MIT
Platform: UNKNOWN
Classifier: Development Status :: 4 - Beta
Classifier: Environment :: Other Environment
Classifier: Intended Audience :: Developers
Classifier: License :: OSI Approved :: MIT License
Classifier: Operating System :: OS Independent
Classifier: Programming Language :: Python
Classifier: Programming Language :: Python :: 3
Classifier: Programming Language :: Python :: 3.5
Classifier: Programming Language :: Python :: 3.6
Classifier: Programming Language :: Python :: 3.7
Classifier: Programming Language :: Python :: 3.8
Classifier: Programming Language :: Python :: 3.9
Classifier: Topic :: Software Development :: Libraries :: Python Modules
Requires-Python: ~=3.6
Requires-Dist: betterproto (>=1.2.5)
Requires-Dist: grpclib
Requires-Dist: python-consul2
Requires-Dist: cachetools
Requires-Dist: syncer
